colicoords/__init__.py
colicoords/cell.py
colicoords/config.py
colicoords/daostormIO.py
colicoords/data_models.py
colicoords/fileIO.py
colicoords/fitting.py
colicoords/iplot.py
colicoords/minimizers.py
colicoords/models.py
colicoords/plot.py
colicoords/postprocess.py
colicoords/preprocess.py
colicoords/support.py
colicoords/synthetic_data.py
colicoords/cnn/LICENSE.md
colicoords/cnn/losses.py
colicoords/cnn/preprocess.py
colicoords/cnn/readme.md
colicoords/cnn/unet.py
colicoords/gui/__init__.py
colicoords/gui/controller.py
colicoords/gui/images_select.py
colicoords-0.1.5.dist-info/AUTHORS
colicoords-0.1.5.dist-info/AUTHORS.rst
colicoords-0.1.5.dist-info/LICENSE
colicoords-0.1.5.dist-info/METADATA
colicoords-0.1.5.dist-info/WHEEL
colicoords-0.1.5.dist-info/pbr.json
colicoords-0.1.5.dist-info/top_level.txt
colicoords-0.1.5.dist-info/RECORD
