Metadata-Version: 2.1
Name: colicoords
Version: 0.1.5
Summary: Create a coordinate system in rod-shaped cells.
Home-page: https://github.com/Jhsmit/ColiCoords
Author: Jochem Smit
Author-email: jhmit@gmail.com
License: MIT
Keywords: cells microscopy ecoli coordinates
Platform: UNKNOWN
Classifier: Development Status :: 4 - Beta
Classifier: Intended Audience :: Science/Research
Classifier: Framework :: Jupyter
Classifier: License :: OSI Approved :: MIT License
Classifier: Topic :: Scientific/Engineering :: Bio-Informatics
Classifier: Programming Language :: Python :: 3.6
Requires-Python: >=3.6
Requires-Dist: numpy
Requires-Dist: matplotlib (>=2.2.0)
Requires-Dist: seaborn
Requires-Dist: mahotas
Requires-Dist: multiprocess
Requires-Dist: scipy
Requires-Dist: h5py
Requires-Dist: tifffile
Requires-Dist: tqdm (>=4.27.0)
Requires-Dist: symfit (>=0.4.6)
Requires-Dist: ipywidgets
Requires-Dist: IPython
